{
  "display": {
    "icon": {
      "item": "bettermcdonaldsmod:big_mac"
    },
    "title": {
      "translate": "advancement.bettermcdonaldsmod.craft_burger.title"
    },
    "description": {
      "translate": "advancement.bettermcdonaldsmod.craft_burger.description"
    },
    "frame": "goal",
    "show_toast": true,
    "announce_to_chat": true,
    "hidden": false
  },
  "criteria": {
    "craft_burger_advancement": {
      "trigger": "minecraft:inventory_changed",
      "conditions": {
        "items": [
          {
            "tags": [
              "bettermcdonaldsmod:burgers"
            ],
            "count": {
              "min": 1,
              "max": 64
            }
          }
        ]
      }
    }
  },
  "parent": "bettermcdonaldsmod:craft_knife"
}